vectorcode-0.7.20.dist-info/METADATA
vectorcode-0.7.20.dist-info/WHEEL
vectorcode-0.7.20.dist-info/entry_points.txt
vectorcode-0.7.20.dist-info/licenses/LICENSE
vectorcode/__init__.py
vectorcode/_version.py
vectorcode/chunking.py
vectorcode/cli_utils.py
vectorcode/common.py
vectorcode/debugging.py
vectorcode/lsp_main.py
vectorcode/main.py
vectorcode/mcp_main.py
vectorcode/subcommands/__init__.py
vectorcode/subcommands/check.py
vectorcode/subcommands/chunks.py
vectorcode/subcommands/clean.py
vectorcode/subcommands/drop.py
vectorcode/subcommands/files/__init__.py
vectorcode/subcommands/files/ls.py
vectorcode/subcommands/files/rm.py
vectorcode/subcommands/init.py
vectorcode/subcommands/ls.py
vectorcode/subcommands/prompt.py
vectorcode/subcommands/query/__init__.py
vectorcode/subcommands/query/reranker/__init__.py
vectorcode/subcommands/query/reranker/base.py
vectorcode/subcommands/query/reranker/cross_encoder.py
vectorcode/subcommands/query/reranker/naive.py
vectorcode/subcommands/query/types.py
vectorcode/subcommands/update.py
vectorcode/subcommands/vectorise.py
vectorcode-0.7.20.dist-info/RECORD
