Metadata-Version: 2.1
Name: VectorCode
Version: 0.7.20
Summary: A tool to vectorise repositories for RAG.
Author-Email: Davidyz <hzjlyz@gmail.com>
License: MIT
Project-URL: homepage, https://github.com/Davidyz/VectorCode
Project-URL: github, https://github.com/Davidyz/VectorCode
Project-URL: documentation, https://github.com/Davidyz/VectorCode/blob/main/docs/cli.md
Requires-Python: <3.14,>=3.11
Requires-Dist: chromadb<=0.6.3
Requires-Dist: sentence-transformers
Requires-Dist: pathspec
Requires-Dist: tabulate
Requires-Dist: shtab
Requires-Dist: numpy
Requires-Dist: psutil
Requires-Dist: httpx
Requires-Dist: tree-sitter!=0.25.0
Requires-Dist: tree-sitter-language-pack
Requires-Dist: pygments
Requires-Dist: transformers!=4.51.0,!=4.51.1,!=4.51.2,>=4.36.0
Requires-Dist: wheel<0.46.0
Requires-Dist: colorlog
Requires-Dist: charset-normalizer>=3.4.1
Requires-Dist: json5
Requires-Dist: posthog<6.0.0
Requires-Dist: filelock>=3.15.0
Provides-Extra: legacy
Requires-Dist: numpy<2.0.0; extra == "legacy"
Requires-Dist: torch==2.2.2; extra == "legacy"
Requires-Dist: transformers<=4.49.0; extra == "legacy"
Provides-Extra: intel
Requires-Dist: optimum[openvino]; extra == "intel"
Requires-Dist: openvino; extra == "intel"
Provides-Extra: lsp
Requires-Dist: pygls<2.0.0; extra == "lsp"
Requires-Dist: lsprotocol; extra == "lsp"
Provides-Extra: mcp
Requires-Dist: mcp<2.0.0; extra == "mcp"
Requires-Dist: pydantic; extra == "mcp"
Provides-Extra: debug
Requires-Dist: coredumpy>=0.4.1; extra == "debug"
